physlp/__init__.py
physlp/modules/__init__.py
physlp/py.typed
physlp/routines/__init__.py
physlp-0.1.8.dist-info/WHEEL
physlp-0.1.8.dist-info/METADATA
physlp-0.1.8.dist-info/RECORD
