Metadata-Version: 2.3
Name: physlp
Version: 0.1.8
Summary: A library providing tools for basic physics.
Requires-Dist: corelp
Requires-Python: >=3.12
